infi.projector-1.1-py3.7-nspkg.pth
infi/projector/__init__.py
infi/projector/__version__.py
infi/projector/commandline_parser/__init__.py
infi/projector/helper/__init__.py
infi/projector/helper/assertions/__init__.py
infi/projector/helper/utils/__init__.py
infi/projector/helper/utils/package_sets/__init__.py
infi/projector/plugins/__init__.py
infi/projector/plugins/builtins/__init__.py
infi/projector/plugins/builtins/console_scripts/__init__.py
infi/projector/plugins/builtins/devenv/__init__.py
infi/projector/plugins/builtins/gui_scripts/__init__.py
infi/projector/plugins/builtins/isolated_python/__init__.py
infi/projector/plugins/builtins/js_requirements/__init__.py
infi/projector/plugins/builtins/package_data/__init__.py
infi/projector/plugins/builtins/package_scripts/__init__.py
infi/projector/plugins/builtins/repository/__init__.py
infi/projector/plugins/builtins/repository/skeleton/.gitignore
infi/projector/plugins/builtins/repository/skeleton/README.md
infi/projector/plugins/builtins/repository/skeleton/__init__.py
infi/projector/plugins/builtins/repository/skeleton/bootstrap.py
infi/projector/plugins/builtins/repository/skeleton/buildout.cfg
infi/projector/plugins/builtins/repository/skeleton/get-pip.py
infi/projector/plugins/builtins/repository/skeleton/setup.in
infi/projector/plugins/builtins/requirements/__init__.py
infi/projector/plugins/builtins/submodules/__init__.py
infi/projector/plugins/builtins/version/__init__.py
infi/projector/scripts/__init__.py
infi.projector-1.1.dist-info/LICENSE
infi.projector-1.1.dist-info/METADATA
infi.projector-1.1.dist-info/WHEEL
infi.projector-1.1.dist-info/entry_points.txt
infi.projector-1.1.dist-info/namespace_packages.txt
infi.projector-1.1.dist-info/top_level.txt
infi.projector-1.1.dist-info/RECORD
