Metadata-Version: 2.1
Name: infi.projector
Version: 1.1
Summary: Python project management tool
Home-page: https://github.com/Infinidat/infi.projector
Author: Arnon Yaari
Author-email: arnony@infinidat.com
License: BSD
Platform: UNKNOWN
Classifier: Intended Audience :: Developers
Classifier: Intended Audience :: System Administrators
Classifier: License :: OSI Approved :: BSD License
Classifier: Operating System :: OS Independent
Classifier: Programming Language :: Python
Classifier: Programming Language :: Python :: 2
Classifier: Programming Language :: Python :: 3
Classifier: Topic :: Software Development :: Libraries :: Python Modules
Requires-Dist: docopt
Requires-Dist: git-py
Requires-Dist: infi.execute
Requires-Dist: infi.recipe.python
Requires-Dist: infi.recipe.template.version
Requires-Dist: pip
Requires-Dist: setuptools
Requires-Dist: six
Requires-Dist: twine (<=1.15.0)
Requires-Dist: wheel
Requires-Dist: zc.buildout (>=2.9.2)
